pyninjas/__init__.py
pyninjas/blog/__init__.py
pyninjas/blog/admin.py
pyninjas/blog/apps.py
pyninjas/blog/context_processors.py
pyninjas/blog/forms.py
pyninjas/blog/models.py
pyninjas/blog/urls.py
pyninjas/blog/views.py
pyninjas/blog/widgets.py
pyninjas/blog/migrations/0001_initial.py
pyninjas/blog/migrations/0002_post_published_at.py
pyninjas/blog/migrations/0003_auto_20180322_1443.py
pyninjas/blog/migrations/__init__.py
pyninjas/blog/static/blog/blog.css
pyninjas/blog/templates/blog/article.html
pyninjas/blog/templates/blog/base.html
pyninjas/blog/templates/blog/index.html
pyninjas_blog-0.0.2.dist-info/DESCRIPTION.rst
pyninjas_blog-0.0.2.dist-info/LICENSE.txt
pyninjas_blog-0.0.2.dist-info/METADATA
pyninjas_blog-0.0.2.dist-info/RECORD
pyninjas_blog-0.0.2.dist-info/WHEEL
pyninjas_blog-0.0.2.dist-info/metadata.json
pyninjas_blog-0.0.2.dist-info/top_level.txt
