Metadata-Version: 2.0
Name: pyninjas-blog
Version: 0.0.2
Summary: Simple Blog Application for Django
Home-page: https://github.com/pyninjas/pyninjas-blog
Author: Emin Mastizada
Author-email: emin@linux.com
License: MIT
Project-URL: Bug Reports, https://github.com/pyninjas/pyninjas-blog/issues
Project-URL: Source, https://github.com/pyninjas/pyninjas-blog
Project-URL: Say Thanks!, https://saythanks.io/to/mastizada
Keywords: blog,django,pyninjas,simple
Platform: UNKNOWN
Classifier: Development Status :: 4 - Beta
Classifier: License :: OSI Approved :: MIT License
Classifier: Operating System :: OS Independent
Classifier: Programming Language :: Python
Classifier: Programming Language :: Python :: 3.6
Classifier: Programming Language :: Python :: 3.7
Classifier: Programming Language :: Python :: 3 :: Only
Classifier: Topic :: Software Development :: Libraries :: Python Modules
Classifier: Environment :: Web Environment
Classifier: Framework :: Django
Classifier: Framework :: Django :: 1.11
Classifier: Framework :: Django :: 2.0
Requires-Dist: Django (>=1.11)
Requires-Dist: Pillow (>=3.0.0)
